MANIFEST.in
README.rst
rst2epub.py
setup.py
epublib/__init__.py
epublib/epub.py
epublib/epub_flymake.py
epublib/mobi.py
epublib/templates/container.xml
epublib/templates/content.opf
epublib/templates/ez-section.html
epublib/templates/image.html
epublib/templates/kindle.css
epublib/templates/main.Nov2012.css
epublib/templates/main.Nov21.css
epublib/templates/main.css
epublib/templates/mainOLD.css
epublib/templates/mobicomic.html
epublib/templates/mobicomic2.html
epublib/templates/title-page.html
epublib/templates/toc.html
epublib/templates/toc.ncx
rst2epub2.egg-info/PKG-INFO
rst2epub2.egg-info/SOURCES.txt
rst2epub2.egg-info/dependency_links.txt
rst2epub2.egg-info/not-zip-safe
rst2epub2.egg-info/requires.txt
rst2epub2.egg-info/top_level.txt