Metadata-Version: 1.1
Name: rst2epub2
Version: 0.3.1
Summary: script/library to create epubs programatically and from rst
Home-page: https://github.com/mattharrison/rst2epub2
Author: matt harrison
Author-email: matthewharrison AT gmail
License: UNKNOWN
Platform: UNKNOWN
Classifier: Programming Language :: Python
Classifier: Programming Language :: Python :: 2.6
Classifier: Programming Language :: Python :: 2.7
